Workbook

Sheet Assumptions
A1: Parameter | B1: Value
A2: VAT rate | B2: 0.2
A3: Commission rate | B3: 0.075
A4: Discount tier | B4: 0.05

Sheet Sales
A1: Rep | B1: Region | C1: Units | D1: Unit Price | E1: Gross | F1: VAT | G1: Net | H1: Commission | I1: Band
A2: Rep 1 | B2: AMER | C2: 102 | D2: 19.99 | E2: =C2*D2 | F2: =E2*Assumptions!$B$2 | G2: =E2-F2 | H2: =ROUND(G2*Assumptions!$B$3,2) | I2: =IF(C2>150,"High",IF(C2>120,"Mid","Low"))
A3: Rep 2 | B3: EMEA | C3: 103 | D3: 19.99 | E3: =C3*D3 | F3: =E3*Assumptions!$B$2 | G3: =E3-F3 | H3: =ROUND(G3*Assumptions!$B$3,2) | I3: =IF(C3>150,"High",IF(C3>120,"Mid","Low"))
A4: Rep 3 | B4: AMER | C4: 104 | D4: 19.99 | E4: =C4*D4 | F4: =E4*Assumptions!$B$2 | G4: =E4-F4 | H4: =ROUND(G4*Assumptions!$B$3,2) | I4: =IF(C4>150,"High",IF(C4>120,"Mid","Low"))
A5: Rep 4 | B5: EMEA | C5: 105 | D5: 19.99 | E5: =C5*D5 | F5: =E5*Assumptions!$B$2 | G5: =E5-F5 | H5: =ROUND(G5*Assumptions!$B$3,2) | I5: =IF(C5>150,"High",IF(C5>120,"Mid","Low"))
A6: Rep 5 | B6: AMER | C6: 106 | D6: 19.99 | E6: =C6*D6 | F6: =E6*Assumptions!$B$2 | G6: =E6-F6 | H6: =ROUND(G6*Assumptions!$B$3,2) | I6: =IF(C6>150,"High",IF(C6>120,"Mid","Low"))
A7: Rep 6 | B7: EMEA | C7: 107 | D7: 19.99 | E7: =C7*D7 | F7: =E7*Assumptions!$B$2 | G7: =E7-F7 | H7: =ROUND(G7*Assumptions!$B$3,2) | I7: =IF(C7>150,"High",IF(C7>120,"Mid","Low"))
A8: Rep 7 | B8: AMER | C8: 108 | D8: 19.99 | E8: =C8*D8 | F8: =E8*Assumptions!$B$2 | G8: =E8-F8 | H8: =ROUND(G8*Assumptions!$B$3,2) | I8: =IF(C8>150,"High",IF(C8>120,"Mid","Low"))
A9: Rep 8 | B9: EMEA | C9: 109 | D9: 19.99 | E9: =C9*D9 | F9: =E9*Assumptions!$B$2 | G9: =E9-F9 | H9: =ROUND(G9*Assumptions!$B$3,2) | I9: =IF(C9>150,"High",IF(C9>120,"Mid","Low"))
A10: Rep 9 | B10: AMER | C10: 110 | D10: 19.99 | E10: =C10*D10 | F10: =E10*Assumptions!$B$2 | G10: =E10-F10 | H10: =ROUND(G10*Assumptions!$B$3,2) | I10: =IF(C10>150,"High",IF(C10>120,"Mid","Low"))
A11: Rep 10 | B11: EMEA | C11: 111 | D11: 19.99 | E11: =C11*D11 | F11: =E11*Assumptions!$B$2 | G11: =E11-F11 | H11: =ROUND(G11*Assumptions!$B$3,2) | I11: =IF(C11>150,"High",IF(C11>120,"Mid","Low"))
A12: Rep 11 | B12: AMER | C12: 112 | D12: 19.99 | E12: =C12*D12 | F12: =E12*Assumptions!$B$2 | G12: =E12-F12 | H12: =ROUND(G12*Assumptions!$B$3,2) | I12: =IF(C12>150,"High",IF(C12>120,"Mid","Low"))
A13: Rep 12 | B13: EMEA | C13: 113 | D13: 19.99 | E13: =C13*D13 | F13: =E13*Assumptions!$B$2 | G13: =E13-F13 | H13: =ROUND(G13*Assumptions!$B$3,2) | I13: =IF(C13>150,"High",IF(C13>120,"Mid","Low"))
... A41: Rep 40 | B41: EMEA | C41: 141 | D41: 19.99 | E41: =C41*D41 | F41: =E41*Assumptions!$B$2 | G41: =E41-F41 | H41: =ROUND(G41*Assumptions!$B$3,2) | I41: =IF(C41>150,"High",IF(C41>120,"Mid","Low"))
E42: =SUM(E2:E41) | G42: =SUM(G2:G41) | H42: =SUM(H2:H41)

Sheet Summary
A1: Metric | B1: Value
A2: Total Gross | B2: =Sales!E42
A3: Total Commission | B3: =Sales!H42
A4: Avg Unit Price | B4: =AVERAGE(Sales!D2:D41)
B5: =VLOOKUP("Rep 1",Sales!A2:I41,5,FALSE)
B6: =INDEX(Sales!G2:G41,MATCH("Rep 3",Sales!A2:A41,0))
B7: =B3/B2*100
B8: =EOMONTH(TODAY(),12)
